mdchat/__init__.py
mdchat/__main__.py
mdchat/chatbot.py
mdchat/cli.py
mdchat/commands/__init__.py
mdchat/commands/chat.py
mdchat/commands/config.py
mdchat/config.py
mdchat/utils.py
mdchat-1.1.1.dist-info/LICENSE
mdchat-1.1.1.dist-info/METADATA
mdchat-1.1.1.dist-info/WHEEL
mdchat-1.1.1.dist-info/entry_points.txt
mdchat-1.1.1.dist-info/RECORD
