Metadata-Version: 2.1
Name: mdchat
Version: 1.1.1
Summary: a CLI that lets you chat with your markdown notes
License: see LICENSE
Author: Mykal Machon
Author-email: mykal@tinybox.dev
Requires-Python: >=3.10,<4.0
Classifier: License :: Other/Proprietary License
Classifier: Programming Language :: Python :: 3
Classifier: Programming Language :: Python :: 3.10
Classifier: Programming Language :: Python :: 3.11
Classifier: Programming Language :: Python :: 3.12
Requires-Dist: faiss-cpu (>=1.7.4,<2.0.0)
Requires-Dist: langchain (>=0.0.345,<0.0.346)
Requires-Dist: openai (>=1.3.7,<2.0.0)
Requires-Dist: rich (>=13.7.0,<14.0.0)
Requires-Dist: tiktoken (>=0.5.2,<0.6.0)
Requires-Dist: typer[all] (>=0.9.0,<0.10.0)
